jsktoolbox/__init__.py
jsktoolbox/attribtool.py
jsktoolbox/basetool/__init__.py
jsktoolbox/basetool/classes.py
jsktoolbox/basetool/data.py
jsktoolbox/basetool/logs.py
jsktoolbox/basetool/threads.py
jsktoolbox/configtool/__init__.py
jsktoolbox/configtool/libs/__init__.py
jsktoolbox/configtool/libs/data.py
jsktoolbox/configtool/libs/file.py
jsktoolbox/configtool/main.py
jsktoolbox/datetool.py
jsktoolbox/devices/__init__.py
jsktoolbox/devices/libs/__init__.py
jsktoolbox/devices/libs/base.py
jsktoolbox/devices/libs/converters.py
jsktoolbox/devices/mikrotik/__init__.py
jsktoolbox/devices/mikrotik/base.py
jsktoolbox/devices/mikrotik/elements/__init__.py
jsktoolbox/devices/mikrotik/elements/certificate.py
jsktoolbox/devices/mikrotik/elements/disk.py
jsktoolbox/devices/mikrotik/elements/file.py
jsktoolbox/devices/mikrotik/elements/interface.py
jsktoolbox/devices/mikrotik/elements/ip.py
jsktoolbox/devices/mikrotik/elements/ipv6.py
jsktoolbox/devices/mikrotik/elements/lcd.py
jsktoolbox/devices/mikrotik/elements/libs/__init__.py
jsktoolbox/devices/mikrotik/elements/libs/base.py
jsktoolbox/devices/mikrotik/elements/libs/interfaces.py
jsktoolbox/devices/mikrotik/elements/libs/search.py
jsktoolbox/devices/mikrotik/elements/log.py
jsktoolbox/devices/mikrotik/elements/mpls.py
jsktoolbox/devices/mikrotik/elements/partitions.py
jsktoolbox/devices/mikrotik/elements/port.py
jsktoolbox/devices/mikrotik/elements/ppp.py
jsktoolbox/devices/mikrotik/elements/queue.py
jsktoolbox/devices/mikrotik/elements/radius.py
jsktoolbox/devices/mikrotik/elements/routing.py
jsktoolbox/devices/mikrotik/elements/snmp.py
jsktoolbox/devices/mikrotik/elements/system.py
jsktoolbox/devices/mikrotik/elements/tool.py
jsktoolbox/devices/mikrotik/elements/user.py
jsktoolbox/devices/mikrotik/routerboard.py
jsktoolbox/devices/network/__init__.py
jsktoolbox/devices/network/connectors.py
jsktoolbox/edmctool/__init__.py
jsktoolbox/edmctool/base.py
jsktoolbox/edmctool/data.py
jsktoolbox/edmctool/ed_keys.py
jsktoolbox-1.2.2.dist-info/LICENSE
jsktoolbox-1.2.2.dist-info/METADATA
jsktoolbox-1.2.2.dist-info/WHEEL
jsktoolbox-1.2.2.dist-info/entry_points.txt
jsktoolbox-1.2.2.dist-info/RECORD
