Metadata-Version: 2.3
Name: jsktoolbox
Version: 1.2.2
Summary: Small sets of classes for various operations.
License: MIT
Author: Jacek 'Szumak' Kotlarski
Author-email: szumak@virthost.pl
Maintainer: Jacek 'Szumak' Kotlarski
Maintainer-email: szumak@virthost.pl
Requires-Python: >=3.10,<4.0
Classifier: License :: OSI Approved :: MIT License
Classifier: Programming Language :: Python :: 3
Classifier: Programming Language :: Python :: 3.10
Classifier: Programming Language :: Python :: 3.11
Classifier: Programming Language :: Python :: 3.12
Classifier: Programming Language :: Python :: 3.13
Classifier: Topic :: Software Development :: Libraries
Requires-Dist: requests (>=2.32.4,<3.0.0)
Requires-Dist: urllib3 (>=2.5.0,<3.0.0)
Project-URL: Documentation, https://app.readthedocs.org/projects/jsktoolbox/
Project-URL: Homepage, https://github.com/Szumak75/JskToolBox
Project-URL: Repository, https://github.com/Szumak75/JskToolBox/tree/1.2.2
